neoload_compose/__init__.py
neoload_compose/__main__.py
neoload_compose/version.py
neoload_compose/commands/__init__.py
neoload_compose/commands/config.py
neoload_compose/commands/constant.py
neoload_compose/commands/current.py
neoload_compose/commands/delay.py
neoload_compose/commands/duration.py
neoload_compose/commands/examples.py
neoload_compose/commands/extract.py
neoload_compose/commands/header.py
neoload_compose/commands/http.py
neoload_compose/commands/import.py
neoload_compose/commands/ramp.py
neoload_compose/commands/reset.py
neoload_compose/commands/run.py
neoload_compose/commands/sla.py
neoload_compose/commands/transaction.py
neoload_compose/commands/undo.py
neoload_compose/commands/validate.py
neoload_compose/compose_lib/builder_data.py
neoload_compose/compose_lib/command_category.py
neoload_compose/compose_lib/common.py
neoload_compose/compose_lib/profile.py
resources/__init__.py
resources/examples.txt
resources/dist/__init__.py
resources/dist/jinja/__init__.py
resources/dist/jinja/builtin-console-summary.j2
neoload_compose-0.1.4.dist-info/LICENSE
neoload_compose-0.1.4.dist-info/METADATA
neoload_compose-0.1.4.dist-info/WHEEL
neoload_compose-0.1.4.dist-info/entry_points.txt
neoload_compose-0.1.4.dist-info/top_level.txt
neoload_compose-0.1.4.dist-info/RECORD
