Metadata-Version: 2.1
Name: neoload-compose
Version: 0.1.4
Summary: A command-line native utility for creating NeoLoad performance tests
Home-page: https://github.com/Neotys-Connect/neoload-compose
Author: Paul Bruce
Author-email: 
License: Apache 2.0
Platform: UNKNOWN
Requires-Dist: click (>=7)
Requires-Dist: pyconfig
Requires-Dist: appdirs
Requires-Dist: requests
Requires-Dist: jsonschema
Requires-Dist: PyYAML (>=5)
Requires-Dist: pytest
Requires-Dist: pytest-datafiles
Requires-Dist: junit-xml
Requires-Dist: termcolor
Requires-Dist: coloredlogs
Requires-Dist: gitignore-parser
Requires-Dist: tqdm
Requires-Dist: requests-toolbelt
Requires-Dist: urllib3
Requires-Dist: neoload
Requires-Dist: colorama
Requires-Dist: ruamel.yaml
Requires-Dist: jsonpickle
Requires-Dist: importlib-resources
